{
    "num": 455271,
    "name": "【イカれた約束】ザック＆レイ",
    "rarity": "UR",
    "types": [
        "防"
    ],
    "cool_time": 30,
    "activation": "短",
    "attribute": "水",
    "rank": "コラボガチャ",
    "ability": "被ダメージを80%減らす（8秒間）",
    "atk": {
        "lv01": 69,
        "lv20": 142,
        "lv30": 181,
        "lv40": 219,
        "lv50": 258,
        "lv60": 297
    },
    "def": {
        "lv01": 22,
        "lv20": 46,
        "lv30": 59,
        "lv40": 72,
        "lv50": 84,
        "lv60": 97
    },
    "phs": {
        "lv01": 448,
        "lv20": 928,
        "lv30": 1181,
        "lv40": 1434,
        "lv50": 1686,
        "lv60": 1939
    },
    "note": "コラボ",
    "theme": "殺戮の天使"
}