{
    "num": 455284,
    "name": "∗振付ノ美∗ オルケーシス",
    "rarity": "SR",
    "types": [
        "近",
        "奪"
    ],
    "cool_time": 26,
    "activation": "無",
    "attribute": "水",
    "rank": "C",
    "ability": "前方攻撃+ダメージの70%ライフ吸収（小ダメージ）",
    "atk": {
        "lv01": 64,
        "lv20": 123,
        "lv30": 154,
        "lv40": 184,
        "lv50": 215,
        "lv60": 246
    },
    "def": {
        "lv01": 21,
        "lv20": 40,
        "lv30": 50,
        "lv40": 60,
        "lv50": 70,
        "lv60": 80
    },
    "phs": {
        "lv01": 419,
        "lv20": 803,
        "lv30": 1004,
        "lv40": 1206,
        "lv50": 1408,
        "lv60": 1609
    },
    "note": "通常",
    "theme": "ポロロッチョ"
}