{
    "num": 455399,
    "name": "【4周年ありがとう】全員集合記念パーティ",
    "rarity": "UR",
    "types": [
        "癒",
        "全"
    ],
    "cool_time": 996,
    "activation": "短",
    "attribute": "火",
    "rank": "シーズン報酬",
    "ability": "味方チーム全員のライフを100%回復",
    "atk": {
        "lv01": 23,
        "lv20": 48,
        "lv30": 0,
        "lv40": 0,
        "lv50": 0,
        "lv60": 0
    },
    "def": {
        "lv01": 9,
        "lv20": 19,
        "lv30": 0,
        "lv40": 0,
        "lv50": 0,
        "lv60": 0
    },
    "phs": {
        "lv01": 280,
        "lv20": 580,
        "lv30": 0,
        "lv40": 0,
        "lv50": 0,
        "lv60": 0
    },
    "note": "シーズン報酬",
    "theme": "4周年記念"
}