{
    "num": 455318,
    "name": "背に負いし亡き妻の加護",
    "rarity": "UR",
    "types": [
        "防",
        "吸"
    ],
    "cool_time": 30,
    "activation": "無",
    "attribute": "火",
    "rank": "S1",
    "ability": "被ダメージを ライフに変換する（3秒間）",
    "atk": {
        "lv01": 66,
        "lv20": 134,
        "lv30": 170,
        "lv40": 206,
        "lv50": 242,
        "lv60": 278
    },
    "def": {
        "lv01": 27,
        "lv20": 56,
        "lv30": 71,
        "lv40": 86,
        "lv50": 101,
        "lv60": 116
    },
    "phs": {
        "lv01": 437,
        "lv20": 893,
        "lv30": 1133,
        "lv40": 1373,
        "lv50": 1614,
        "lv60": 1854
    },
    "note": "通常",
    "theme": "ルチアーノ"
}