{
    "num": 455378,
    "name": "【ダンまち】眷族の物語(ファミリア・ミィス)",
    "rarity": "UR",
    "types": [
        "癒",
        "続"
    ],
    "cool_time": 35,
    "activation": "短",
    "attribute": "火",
    "rank": "コラボガチャ",
    "ability": "ライフを持続回復（10秒間で最大120％）",
    "atk": {
        "lv01": 43,
        "lv20": 90,
        "lv30": 114,
        "lv40": 138,
        "lv50": 163,
        "lv60": 187
    },
    "def": {
        "lv01": 22,
        "lv20": 45,
        "lv30": 57,
        "lv40": 69,
        "lv50": 81,
        "lv60": 94
    },
    "phs": {
        "lv01": 661,
        "lv20": 1369,
        "lv30": 1742,
        "lv40": 2115,
        "lv50": 2488,
        "lv60": 2860
    },
    "note": "コラボ",
    "theme": "ダンまち"
}