{
    "num": 455354,
    "name": "#夜光犯罪特区 #メビウス目撃情報",
    "rarity": "SR",
    "types": [
        "連",
        "奪"
    ],
    "cool_time": 26,
    "activation": "無",
    "attribute": "火",
    "rank": "A",
    "ability": "連続攻撃+ダメージの70％ライフ吸収（中ダメージ）",
    "atk": {
        "lv01": 68,
        "lv20": 129,
        "lv30": 161,
        "lv40": 193,
        "lv50": 226,
        "lv60": 258
    },
    "def": {
        "lv01": 22,
        "lv20": 42,
        "lv30": 53,
        "lv40": 63,
        "lv50": 74,
        "lv60": 84
    },
    "phs": {
        "lv01": 442,
        "lv20": 843,
        "lv30": 1054,
        "lv40": 1265,
        "lv50": 1476,
        "lv60": 1687
    },
    "note": "通常",
    "theme": "零夜"
}