{
    "num": 455462,
    "name": "熱血！猛進！配給支援部隊 Mr.ランチャー",
    "rarity": "SR",
    "types": [
        "返"
    ],
    "cool_time": 28,
    "activation": "無",
    "attribute": "木",
    "rank": "B",
    "ability": "4秒間最初に受けた攻撃を無効化し周囲の敵にカウンター攻撃（小ダメージ）",
    "atk": {
        "lv01": 61,
        "lv20": 116,
        "lv30": 145,
        "lv40": 174,
        "lv50": 204,
        "lv60": 233
    },
    "def": {
        "lv01": 25,
        "lv20": 48,
        "lv30": 61,
        "lv40": 73,
        "lv50": 85,
        "lv60": 97
    },
    "phs": {
        "lv01": 405,
        "lv20": 774,
        "lv30": 968,
        "lv40": 1163,
        "lv50": 1357,
        "lv60": 1551
    },
    "note": "通常",
    "theme": "GBG"
}